student_management/__init__.py
student_management/graduate.py
student_management/parent_student.py
student_management/phd.py
student_management/undergraduate.py
student_management_basic-0.1.0.dist-info/METADATA
student_management_basic-0.1.0.dist-info/WHEEL
student_management_basic-0.1.0.dist-info/top_level.txt
student_management_basic-0.1.0.dist-info/RECORD
