Metadata-Version: 2.4
Name: student-management-basic
Version: 0.1.0
Summary: Simple student management abstractions (Undergraduate, Graduate, PhD)
Author-email: Md Aman Khan <email@example.com>
Project-URL: Homepage, https://github.com/aman2712/student_management
Classifier: Programming Language :: Python :: 3
Classifier: License :: OSI Approved :: MIT License
Classifier: Operating System :: OS Independent
Requires-Python: >=3.8
